cm_portal/__init__.py
cm_portal/admin.py
cm_portal/apps.py
cm_portal/forms.py
cm_portal/models.py
cm_portal/signals.py
cm_portal/tables.py
cm_portal/tests.py
cm_portal/urls.py
cm_portal/views.py
cm_portal/migrations/0001_initial.py
cm_portal/migrations/0002_resident_philhealth.py
cm_portal/migrations/0003_auto_20190503_1215.py
cm_portal/migrations/0004_auto_20190711_2344.py
cm_portal/migrations/0005_building.py
cm_portal/migrations/0006_auto_20190720_0346.py
cm_portal/migrations/0007_resident_residence.py
cm_portal/migrations/0008_remove_resident_building.py
cm_portal/migrations/0009_auto_20190808_1047.py
cm_portal/migrations/0010_auto_20190808_1132.py
cm_portal/migrations/0011_auto_20190825_0411.py
cm_portal/migrations/__init__.py
cm_portal/static/css/animate.css
cm_portal/static/css/bootstrap-4-navbar.css
cm_portal/static/css/bootstrap-4-navbar.min.css
cm_portal/static/css/styles.css
cm_portal/static/images/21.jpg
cm_portal/static/images/avatar.png
cm_portal/static/images/emblem.jpg
cm_portal/static/images/mission-cover.jpg
cm_portal/static/images/new-bldg.jpg
cm_portal/static/images/vision-cover.jpg
cm_portal/static/js/bootstrap-4-navbar.js
cm_portal/static/js/bootstrap-4-navbar.min.js
cm_portal/static/js/jquery.bootstrap.modal.forms.js
cm_portal/static/js/jquery.bootstrap.modal.forms.min.js
cm_portal/static/js/obj_list.js
cm_portal/templates/cm_portal/base.html
cm_portal/templates/cm_portal/base.html~
cm_portal/templates/cm_portal/building_confirm_delete.html
cm_portal/templates/cm_portal/building_detail.html
cm_portal/templates/cm_portal/building_form.html
cm_portal/templates/cm_portal/building_list.html
cm_portal/templates/cm_portal/building_list.html~
cm_portal/templates/cm_portal/building_update_form.html
cm_portal/templates/cm_portal/change_password.html
cm_portal/templates/cm_portal/charge_confirm_delete.html
cm_portal/templates/cm_portal/charge_detail.html
cm_portal/templates/cm_portal/charge_form.html
cm_portal/templates/cm_portal/charge_list.html
cm_portal-0.2.4.dist-info/LICENSE
cm_portal-0.2.4.dist-info/METADATA
cm_portal-0.2.4.dist-info/WHEEL
cm_portal-0.2.4.dist-info/top_level.txt
cm_portal-0.2.4.dist-info/RECORD
