Metadata-Version: 2.1
Name: cm-portal
Version: 0.2.4
Summary: A Django Web App for a Nursing Home Facility
Home-page: https://github.com/ryesalvador/cm_portal/
Author: Rye Salvador
Author-email: salvadorrye@gmail.com
License: GPLv3
Platform: UNKNOWN
Classifier: Environment :: Web Environment
Classifier: Framework :: Django
Classifier: Framework :: Django :: 2.1
Classifier: Intended Audience :: Developers
Classifier: License :: OSI Approved :: GNU General Public License v3 (GPLv3)
Classifier: Operating System :: OS Independent
Classifier: Programming Language :: Python
Classifier: Programming Language :: Python :: 3.6
Classifier: Programming Language :: Python :: 3.7
Classifier: Topic :: Internet :: WWW/HTTP
Classifier: Topic :: Internet :: WWW/HTTP :: Dynamic Content
Requires-Dist: django
Requires-Dist: Pillow
Requires-Dist: django-widget-tweaks
Requires-Dist: django-tables2
Requires-Dist: django-simple-search
Requires-Dist: django-bootstrap-modal-forms
Requires-Dist: django-autocomplete-light
